{
  "pages": {
    "Home": [
      {
        "content": [
          {
            "text": "Wat wilt u melden?",
            "type": "textbox",
            "color": "purple"
          },
          {
            "name": "Ongeval",
            "type": "button",
            "image_url": "category-FirstAid.png"
          },
          {
            "name": "Vechtpartij",
            "type": "button",
            "image_url": "category-fight.png"
          },
          {
            "name": "Wapens",
            "type": "button",
            "image_url": "category-weapons.png"
          },
          {
            "name": "Drugs",
            "type": "button",
            "image_url": "category-drugs.png"
          },
          {
            "name": "Diefstal",
            "type": "button",
            "image_url": "category-theft.png"
          },
          {
            "name": "Pesten",
            "type": "button",
            "image_url": "category-bullying.png"
          },
          {
            "name": "Overlast",
            "type": "button",
            "image_url": "category-nuisance.png"
          },
          {
            "name": "Overige",
            "type": "button",
            "image_url": "category-other.png"
          }
        ]
      }
    ],
    "Ongeval": [
      {
        "content": [
          {
            "text": "Ongeval",
            "type": "textbox",
            "color": "purple"
          },
          {
            "type": "form",
            "formAction": "formSubmit",
            "content": [
              {
                "text": "Foto toevoegen",
                "type": "upload",
                "name": "test"
              },
              {
                "text": "Is het slachtoffer bewusteloos?",
                "type": "radioButtons",
                "name": "unconscious",
                "options": [
                  {
                    "optie": "Ja",
                    "text": "ja"
                  },
                  {
                    "optie": "Nee",
                    "text": "nee"
                  }
                ]
              },
              {
                "type": "radioButtons",
                "text": "Is er een voertuig bij betrokken?",
                "name": "voertuigToggle",
                "toggle": "true",
                "target": "voertuig",
                "options": [
                  {
                    "optie": "Ja",
                    "text": "ja"
                  },
                  {
                    "optie": "Nee",
                    "text": "nee"
                  }
                ]
              },
              {
                "text": "Voertuig",
                "type": "textInput",
                "name": "voertuig",
                "toggle": "true",
                "options": [
                  {
                    "name": "voertuigtype",
                    "inputType": "text",
                    "inhoud": "Wat voor voertuig is het?"
                  },
                  {
                    "name": "voertuigmerk",
                    "inputType": "text",
                    "inhoud": "Voertuig merk"
                  },
                  {
                    "name": "voertuigkenteken",
                    "inputType": "text",
                    "inhoud": "Kenteken"
                  },
                  {
                    "name": "voertuigkleur",
                    "inputType": "text",
                    "inhoud": "Kleur van het voertuig"
                  },
                  {
                    "name": "voertuiganders",
                    "inputType": "text",
                    "inhoud": "Heeft het voertuig nog andere opvallende kenmerken?"
                  }
                ]
              },


              {
                "type": "radioButtons",
                "text": "mogen we contact met u opnemen?",
                "name": "contact",
                "toggle": "true",
                "target": "persoon",
                "options": [
                  {
                    "optie": "Ja",
                    "text": "ja"
                  },
                  {
                    "optie": "Nee",
                    "text": "nee"
                  }
                ]
              },
              {
                "text": "contact gegevens",
                "type": "textInput",
                "name": "persoon",
                "toggle": "true",
                "options": [
                  {
                    "name": "naam",
                    "inputType": "text",
                    "inhoud": "naam"
                  },
                  {
                    "name": "email",
                    "inputType": "email",
                    "inhoud": "email"
                  },
                  {
                    "name": "telefoon",
                    "inputType": "Tel",
                    "inhoud": "telefoon"
                  }
                ]
              }
            ]
          }
        ]
      }
    ],
    "Vechtpartij": [
      {
        "content": [
          {
            "text": "Gevecht melden",
            "type": "textbox",
            "color": "purple"
          },
          {
            "type": "form",
            "formAction": "formSubmit",
            "content": [
              
              {
                "text": "hoeveel personen zijn er aan het vechten",
                "type": "textInput",
                "options": [
                  {
                    "name": "vechtNumber",
                    "inputType": "number",
                    "inhoud": "hoeveel mensen vechten er?"
                  }
                ]
              },
              {
                "type": "radioButtons",
                "text": "heeft u een wapen gezien?",
                "name": "wapenToggle",
                "toggle": "true",
                "target": "wapen",
                "options": [
                  {
                    "optie": "Ja",
                    "text": "ja"
                  },
                  {
                    "optie": "Nee",
                    "text": "nee"
                  }
                ]
              },
              {
                "text": "Wapens",
                "type": "textInput",
                "name": "wapen",
                "toggle": "true",
                "options": [
                  {
                    "name": "weaponDescription",
                    "inputType": "text",
                    "inhoud": "Beschrijf de waargenomen wapens"
                  }
                ]
              },
              {
                "text": "mogen we contact met u opnemen?",
                "type": "radioButtons",
                "name": "contact",
                "toggle": "true",
                "target": "persoon",
                "options": [
                  {
                    "optie": "Ja",
                    "text": "ja"
                  },
                  {
                    "optie": "Nee",
                    "text": "nee"
                  }
                ]
              },
              {
                "text": "contact gegevens",
                "type": "textInput",
                "toggle": "true",
                "name": "persoon",
                "options": [
                  {
                    "name": "naam",
                    "inputType": "text",
                    "inhoud": "naam"
                  },
                  {
                    "name": "email",
                    "inputType": "email",
                    "inhoud": "email"
                  },
                  {
                    "name": "telefoon",
                    "inputType": "Tel",
                    "inhoud": "telefoon"
                  }
                ]
              }
            ]
          }
        ]
      }
    ],
    "Wapens": [
      {
        "content": [
          {
            "text": "Wapens",
            "type": "textbox",
            "color": "purple"
          },
          {
            "type": "form",
            "formAction": "formSubmit",
            "content": [
              {
                "text": "wat voor een wapen heeft u gezien",
                "type": "dropDown",
                "name": "wapen",
                "options": [
                  {
                    "name": "geweer",
                    "text": "geweer"
                  },
                  {
                    "name": "mes",
                    "text": "mes"
                  },
                  {
                    "name": "knuppel",
                    "text": "knuppel"
                  }
                ]
              },

              {
                "type": "radioButtons",
                "text": "Moet er een persoon gemeldt worden?",
                "name": "persoonToggle",
                "toggle": "true",
                "target": "verdachte",
                "options": [
                  {
                    "optie": "Ja",
                    "text": "ja"
                  },
                  {
                    "optie": "Nee",
                    "text": "nee"
                  }
                ]
              },
              {
                "text": "Beschrijf de persoon",
                "type": "textInput",
                "name": "verdachte",
                "toggle": "true",
                "options": [
                  {
                    "name": "p2naam",
                    "inputType": "text",
                    "inhoud": "Naam"
                  },
                  {
                    "name": "p2huidskleur",
                    "inputType": "text",
                    "inhoud": "Huidskleur"
                  },
                  {
                    "name": "p2geslacht",
                    "inputType": "text",
                    "inhoud": "Geslacht"
                  },
                  {
                    "name": "p2leeftijd",
                    "inputType": "text",
                    "inhoud": "Leeftijd"
                  },
                  {
                    "name": "p2kleding",
                    "inputType": "text",
                    "inhoud": "Kleding"
                  },
                  {
                    "name": "p2anders",
                    "inputType": "text",
                    "inhoud": "Opvallende kenmerken aan persoon"
                  }
                ]
              },

              {
                "text": " wat kunt u hier verder over vertellen?",
                "type": "textInput",
                "options": [
                  {
                    "name": "extra",
                    "inputType": "text",
                    "inhoud": "extra informatie"
                  }
                ]
              },
              {
                "type": "radioButtons",
                "text": "mogen we contact met u opnemen?",
                "name": "contact",
                "toggle": "true",
                "target": "persoon",
                "options": [
                  {
                    "optie": "Ja",
                    "text": "ja"
                  },
                  {
                    "optie": "Nee",
                    "text": "nee"
                  }
                ]
              },
              {
                "text": "contact gegevens",
                "type": "textInput",
                "toggle": "true",
                "name": "persoon",
                "options": [
                  {
                    "name": "naam",
                    "inputType": "text",
                    "inhoud": "naam"
                  },
                  {
                    "name": "email",
                    "inputType": "email",
                    "inhoud": "email"
                  },
                  {
                    "name": "telefoon",
                    "inputType": "Tel",
                    "inhoud": "telefoon"
                  }
                ]
              }
            ]
          }
        ]
      }
    ],
    "Drugs": [
      {
        "content": [
          {
            "text": "Drugs",
            "type": "textbox",
            "color": "purple"
          },
          {
            "type": "form",
            "formAction": "formSubmit",
            "content": [
              {
                "type": "radioButtons",
                "text": "Wat heeft u gezien?",
                "name": "drugsToggle",
                "toggle": "true",
                "target": "drugs",
                "options": [
                  {
                    "optie": "handel",
                    "text": "handel"
                  },
                  {
                    "optie": "gebruik",
                    "text": "gebruik"
                  },
                  {
                    "optie": "ja",
                    "text": "anders"
                  }
                ]
              },
              {
                "text": "Anders",
                "type": "textInput",
                "name": "drugs",
                "toggle": "true",
                "options": [
                  {
                    "name": "drugsAnders",
                    "inputType": "text",
                    "inhoud": "Wat is er aan de hand?"
                  }
                ]
              },

              {
                "text": "foto's",
                "type": "upload",
                "name": "test"
              },
              {
                "text": "wie heeft u gezien?",
                "type": "textInput",
                "name": "extraPersoon",
                "options": [
                  {
                    "name": "p2naam",
                    "inputType": "text",
                    "inhoud": "Naam"
                  },
                  {
                    "name": "p2huidskleur",
                    "inputType": "text",
                    "inhoud": "Huidskleur"
                  },
                  {
                    "name": "p2geslacht",
                    "inputType": "text",
                    "inhoud": "Geslacht"
                  },
                  {
                    "name": "p2leeftijd",
                    "inputType": "text",
                    "inhoud": "Leeftijd"
                  },
                  {
                    "name": "p2kleding",
                    "inputType": "text",
                    "inhoud": "Kleding"
                  },
                  {
                    "name": "p2anders",
                    "inputType": "text",
                    "inhoud": "Opvallende kenmerken aan persoon"
                  }
                ]
              },
              {
                "type": "radioButtons",
                "text": "Is er een voertuig bij betrokken?",
                "name": "voertuigToggle",
                "toggle": "true",
                "target": "voertuig",
                "options": [
                  {
                    "optie": "Ja",
                    "text": "ja"
                  },
                  {
                    "optie": "Nee",
                    "text": "nee"
                  }
                ]
              },
              {
                "text": "Voertuig",
                "type": "textInput",
                "name": "voertuig",
                "toggle": "true",
                "options": [
                  {
                    "name": "voertuigtype",
                    "inputType": "text",
                    "inhoud": "Wat voor voertuig is het?"
                  },
                  {
                    "name": "voertuigmerk",
                    "inputType": "text",
                    "inhoud": "Voertuig merk"
                  },
                  {
                    "name": "voertuigkenteken",
                    "inputType": "text",
                    "inhoud": "Kenteken"
                  },
                  {
                    "name": "voertuigkleur",
                    "inputType": "text",
                    "inhoud": "Kleur van het voertuig"
                  },
                  {
                    "name": "voertuiganders",
                    "inputType": "text",
                    "inhoud": "Heeft het voertuig nog andere opvallende kenmerken?"
                  }
                ]
              },

              {
                "text": "wat kunt u hier verder over vertellen?",
                "type": "textInput",
                "name": "extra",
                "options": [
                  {
                    "name": "extra",
                    "inputType": "text",
                    "inhoud": "extra informatie"
                  }
                ]
              },

              {
                "type": "radioButtons",
                "text": "mogen we contact met u opnemen?",
                "name": "contact",
                "toggle": "true",
                "target": "persoon",
                "options": [
                  {
                    "optie": "Ja",
                    "text": "ja"
                  },
                  {
                    "optie": "Nee",
                    "text": "nee"
                  }
                ]
              },
              {
                "text": "contact gegevens",
                "type": "textInput",
                "name": "persoon",
                "toggle": "true",
                "options": [
                  {
                    "name": "naam",
                    "inputType": "text",
                    "inhoud": "naam"
                  },
                  {
                    "name": "email",
                    "inputType": "email",
                    "inhoud": "email"
                  },
                  {
                    "name": "telefoon",
                    "inputType": "Tel",
                    "inhoud": "telefoon"
                  }
                ]
              }
            ]
          }
        ]
      }
    ],
    "Diefstal": [
      {
        "content": [
          {
            "text": "Diefstal",
            "type": "textbox",
            "color": "purple"
          },
          {
            "type": "form",
            "formAction": "formSubmit",
            "content": [
              {
                "text": "Wat is er gestolen?",
                "type": "textInput",
                "name": "voorwerp",
                "options": [
                  {
                    "name": "voorwerpDescription",
                    "inputType": "text",
                    "inhoud": "Beschrijf het voorwerp"
                  },
                  {
                    "name": "voorwerpKleur",
                    "inputType": "text",
                    "inhoud": "Kleur van het gestolen voorwerp"
                  },
                  
                  {
                    "name": "voorwerpMerk",
                    "inputType": "text",
                    "inhoud": "Merk"
                  },
                  {
                    "name": "voorwerpInhoud",
                    "inputType": "text",
                    "inhoud": "Inhoud van voorwerp"
                  },
                  {
                    "name": "voorwerpAnders",
                    "inputType": "text",
                    "inhoud": "Andere kenmerken (bijv. achtergond van smartphone)"
                  }
                ]
              },
              {
                "type": "radioButtons",
                "text": "Is er een verdachte?",
                "name": "persoonToggle",
                "toggle": "true",
                "target": "verdachte",
                "options": [
                  {
                    "optie": "Ja",
                    "text": "ja"
                  },
                  {
                    "optie": "Nee",
                    "text": "nee"
                  }
                ]
              },
              {
                "text": "Beschrijf de verdachte",
                "type": "textInput",
                "name": "verdachte",
                "toggle": "true",
                "options": [
                  {
                    "name": "p2naam",
                    "inputType": "text",
                    "inhoud": "Naam"
                  },
                  {
                    "name": "p2huidskleur",
                    "inputType": "text",
                    "inhoud": "Huidskleur"
                  },
                  {
                    "name": "p2geslacht",
                    "inputType": "text",
                    "inhoud": "Geslacht"
                  },
                  {
                    "name": "p2leeftijd",
                    "inputType": "text",
                    "inhoud": "Leeftijd"
                  },
                  {
                    "name": "p2kleding",
                    "inputType": "text",
                    "inhoud": "Kleding"
                  },
                  {
                    "name": "p2anders",
                    "inputType": "text",
                    "inhoud": "Opvallende kenmerken aan persoon"
                  }
                ]
              },

              

              {
                "text": "wat kunt u hier verder over vertellen?",
                "type": "textInput",
                "options": [
                  {
                    "name": "extra",
                    "inputType": "text",
                    "inhoud": "extra informatie"
                  }
                ]
              },


              {
                "type": "radioButtons",
                "text": "mogen we contact met u opnemen?",
                "name": "contact",
                "toggle": "true",
                "target": "persoon",
                "options": [
                  {
                    "optie": "Ja",
                    "text": "ja"
                  },
                  {
                    "optie": "Nee",
                    "text": "nee"
                  }
                ]
              },
              {
                "text": "contact gegevens",
                "type": "textInput",
                "name": "persoon",
                "toggle": "true",
                "options": [
                  {
                    "name": "naam",
                    "inputType": "text",
                    "inhoud": "naam"
                  },
                  {
                    "name": "email",
                    "inputType": "email",
                    "inhoud": "email"
                  },
                  {
                    "name": "telefoon",
                    "inputType": "Tel",
                    "inhoud": "telefoon"
                  }
                ]
              }
            ]
          }
        ]
      }
    ],
    "Pesten": [
      {
        "content": [
          {
            "text": "Pesten",
            "type": "textbox",
            "color": "purple"
          },
          {
            "type": "form",
            "formAction": "formSubmit",
            "content": [
              {
                "type": "radioButtons",
                "text": "Moet er een persoon gemeldt worden?",
                "name": "persoonToggle",
                "toggle": "true",
                "target": "verdachte",
                "options": [
                  {
                    "optie": "Ja",
                    "text": "ja"
                  },
                  {
                    "optie": "Nee",
                    "text": "nee"
                  }
                ]
              },
              {
                "text": "Beschrijf de persoon",
                "type": "textInput",
                "name": "verdachte",
                "toggle": "true",
                "options": [
                  {
                    "name": "p2naam",
                    "inputType": "text",
                    "inhoud": "Naam"
                  },
                  {
                    "name": "p2huidskleur",
                    "inputType": "text",
                    "inhoud": "Huidskleur"
                  },
                  {
                    "name": "p2geslacht",
                    "inputType": "text",
                    "inhoud": "Geslacht"
                  },
                  {
                    "name": "p2leeftijd",
                    "inputType": "text",
                    "inhoud": "Leeftijd"
                  },
                  {
                    "name": "p2kleding",
                    "inputType": "text",
                    "inhoud": "Kleding"
                  },
                  {
                    "name": "p2anders",
                    "inputType": "text",
                    "inhoud": "Opvallende kenmerken aan persoon"
                  }
                ]
              },
              {
                "text": "wat kunt u hier verder over vertellen?",
                "type": "textInput",
                "options": [
                  {
                    "name": "extra",
                    "inputType": "text",
                    "inhoud": "extra informatie"
                  }
                ]
              },

              {
                "type": "radioButtons",
                "text": "mogen we contact met u opnemen?",
                "name": "contact",
                "toggle": "true",
                "target": "persoon",
                "options": [
                  {
                    "optie": "Ja",
                    "text": "ja"
                  },
                  {
                    "optie": "Nee",
                    "text": "nee"
                  }
                ]
              },
              {
                "text": "contact gegevens",
                "type": "textInput",
                "name": "persoon",
                "toggle": "true",
                "options": [
                  {
                    "name": "naam",
                    "inputType": "text",
                    "inhoud": "naam"
                  },
                  {
                    "name": "email",
                    "inputType": "email",
                    "inhoud": "email"
                  },
                  {
                    "name": "telefoon",
                    "inputType": "Tel",
                    "inhoud": "telefoon"
                  }
                ]
              }
            ]
          }
        ]
      }
    ],
    "Overlast": [
      {
        "content": [
          {
            "text": "Overlast",
            "type": "textbox",
            "color": "purple"
          },
          {
            "type": "form",
            "formAction": "formSubmit",
            "content": [
              {
                "type": "radioButtons",
                "text": "Is er een voertuig bij betrokken?",
                "name": "voertuigToggle",
                "toggle": "true",
                "target": "voertuig",
                "options": [
                  {
                    "optie": "Ja",
                    "text": "ja"
                  },
                  {
                    "optie": "Nee",
                    "text": "nee"
                  }
                ]
              },
              {
                "text": "Voertuig",
                "type": "textInput",
                "name": "voertuig",
                "toggle": "true",
                "options": [
                  {
                    "name": "voertuigtype",
                    "inputType": "text",
                    "inhoud": "Wat voor voertuig is het?"
                  },
                  {
                    "name": "voertuigmerk",
                    "inputType": "text",
                    "inhoud": "Voertuig merk"
                  },
                  {
                    "name": "voertuigkenteken",
                    "inputType": "text",
                    "inhoud": "Kenteken"
                  },
                  {
                    "name": "voertuigkleur",
                    "inputType": "text",
                    "inhoud": "Kleur van het voertuig"
                  },
                  {
                    "name": "voertuiganders",
                    "inputType": "text",
                    "inhoud": "Heeft het voertuig nog andere opvallende kenmerken?"
                  }
                ]
              },
              
              {
                "text": " wat kunt u hier verder over vertellen?",
                "type": "textInput",
                "options": [
                  {
                    "name": "extra",
                    "inputType": "text",
                    "inhoud": "extra informatie"
                  }
                ]
              },
              {
                "text": "contact gegevens",
                "type": "textInput",
                "name": "persoon",
                "options": [
                  {
                    "required": "true",
                    "name": "naam",
                    "inputType": "text",
                    "inhoud": "naam"
                  },
                  {
                    "required": "true",
                    "name": "email",
                    "inputType": "email",
                    "inhoud": "email"
                  },
                  {
                    "required": "true",
                    "name": "telefoon",
                    "inputType": "Tel",
                    "inhoud": "telefoon"
                  }
                ]
              }
            ]
          }
        ]
      }
    ],
    "Overige": [
      {
        "content": [
          {
            "text": "Overige",
            "type": "textbox",
            "color": "purple"
          },
          {
            "type": "form",
            "formAction": "formSubmit",
            "content": [
              {
                "text": "wat is het probleem?",
                "type": "textInput",
                "options": [
                  {
                    "name": "extra",
                    "inputType": "text",
                    "inhoud": "Beschrijf het probleem"
                  }
                ]
              },

              {
                "type": "radioButtons",
                "text": "Moet er een persoon gemeldt worden?",
                "name": "persoonToggle",
                "toggle": "true",
                "target": "verdachte",
                "options": [
                  {
                    "optie": "Ja",
                    "text": "ja"
                  },
                  {
                    "optie": "Nee",
                    "text": "nee"
                  }
                ]
              },
              {
                "text": "Beschrijf de persoon",
                "type": "textInput",
                "name": "verdachte",
                "toggle": "true",
                "options": [
                  {
                    "name": "p2naam",
                    "inputType": "text",
                    "inhoud": "Naam"
                  },
                  {
                    "name": "p2huidskleur",
                    "inputType": "text",
                    "inhoud": "Huidskleur"
                  },
                  {
                    "name": "p2geslacht",
                    "inputType": "text",
                    "inhoud": "Geslacht"
                  },
                  {
                    "name": "p2leeftijd",
                    "inputType": "text",
                    "inhoud": "Leeftijd"
                  },
                  {
                    "name": "p2kleding",
                    "inputType": "text",
                    "inhoud": "Kleding"
                  },
                  {
                    "name": "p2anders",
                    "inputType": "text",
                    "inhoud": "Opvallende kenmerken aan persoon"
                  }
                ]
              },

              {
                "type": "radioButtons",
                "text": "Moet er een voertuig gemeldt worden?",
                "name": "voertuigToggle",
                "toggle": "true",
                "target": "voertuig",
                "options": [
                  {
                    "optie": "Ja",
                    "text": "ja"
                  },
                  {
                    "optie": "Nee",
                    "text": "nee"
                  }
                ]
              },
              {
                "text": "Voertuig",
                "type": "textInput",
                "name": "voertuig",
                "toggle": "true",
                "options": [
                  {
                    "name": "voertuigtype",
                    "inputType": "text",
                    "inhoud": "Wat voor voertuig is het?"
                  },
                  {
                    "name": "voertuigmerk",
                    "inputType": "text",
                    "inhoud": "Voertuig merk"
                  },
                  {
                    "name": "voertuigkenteken",
                    "inputType": "text",
                    "inhoud": "Kenteken"
                  },
                  {
                    "name": "voertuigkleur",
                    "inputType": "text",
                    "inhoud": "Kleur van het voertuig"
                  },
                  {
                    "name": "voertuiganders",
                    "inputType": "text",
                    "inhoud": "Heeft het voertuig nog andere opvallende kenmerken?"
                  }
                ]
              },

              {
                "text": "contact gegevens",
                "type": "textInput",
                "name": "persoon",
                "options": [
                  {
                    "required": "true",
                    "name": "naam",
                    "inputType": "text",
                    "inhoud": "naam"
                  },
                  {
                    "required": "true",
                    "name": "email",
                    "inputType": "email",
                    "inhoud": "email"
                  },
                  {
                    "required": "true",
                    "name": "telefoon",
                    "inputType": "Tel",
                    "inhoud": "telefoon"
                  }
                ]
              }
            ]
          }
        ]
      }
    ],
    "Locaties": [
      {
        "type": "locatieForm",
        "formAction": "",
        "content": {
          "Dordrecht": "label",
          "Leerparkpromenade 100": [],
          "Drechtsteden College": [],
          "Samenwerkings Gebouw": [],
          "Wartburgs College": [],
          "Sport Plein": [],
          "Schippers Internaat": [],
          "Karel Lotsyweg": [],
          "Patersweg": [],
          "Duurzaamheidsfabriek": [],
          "Azzurro": [],
          "Betaalde Parkeerplaats": [],
          "Parkeerplek Langs N3": [],
          "Parkeerplaats Langs Spoor": [],
          "Openbare Weg": [],
          "Gorinchem": "label",
          "Mollenburgseweg": [
            "De snoekzone"
          ]
        }
      }
    ]
  }
}